code_audit/__init__.py
code_audit/analyzer.py
code_audit/cli.py
code_audit/reporter.py
code_audit/scanner.py
dev_debt_scanner-0.9.1.dist-info/licenses/LICENSE
dev_debt_scanner-0.9.1.dist-info/METADATA
dev_debt_scanner-0.9.1.dist-info/WHEEL
dev_debt_scanner-0.9.1.dist-info/entry_points.txt
dev_debt_scanner-0.9.1.dist-info/top_level.txt
dev_debt_scanner-0.9.1.dist-info/RECORD
