Metadata-Version: 2.4
Name: dev-debt-scanner
Version: 0.9.1
Summary: A professional technical debt analyzer and security leak scanner
Author-email: Viraj Ravani <viraj.ravani@somaiya.edu>, Visha Yadav <visha.232973201@vcet.edu.in>
License: MIT
Keywords: security,static-analysis,technical-debt,code-audit
Classifier: Programming Language :: Python :: 3
Classifier: License :: OSI Approved :: MIT License
Classifier: Operating System :: OS Independent
Requires-Python: >=3.8
License-File: LICENSE
Dynamic: license-file
